setup.py
SmsServiceOnline/Api.py
SmsServiceOnline/__init__.py
SmsServiceOnline.egg-info/PKG-INFO
SmsServiceOnline.egg-info/SOURCES.txt
SmsServiceOnline.egg-info/dependency_links.txt
SmsServiceOnline.egg-info/not-zip-safe
SmsServiceOnline.egg-info/requires.txt
SmsServiceOnline.egg-info/top_level.txt