Metadata-Version: 2.1
Name: SmsServiceOnline
Version: 1.0.1
Summary: Package for https://sms-service-online.com
Home-page: https://github.com/fxcvd/SmsServiceOnline
Author-email: rzet595@gmail.com
License: UNKNOWN
Platform: UNKNOWN
